{
    "Number of People": [
        {
            "label": "several people",
            "imagenum": [
                "001",
                "002",
                "006",
                "009",
                "019"
            ]
        },
        {
            "label": "one person",
            "imagenum": [
                "008",
                "011",
                "014",
                "022",
                "025"
            ]
        },
        {
            "label": "one person + others",
            "imagenum": [
                "003",
                "007",
                "015",
                "018"
            ]
        },
        {
            "label": "two people",
            "imagenum": [
                "012",
                "024"
            ]
        },
        {
            "label": "two people + others",
            "imagenum": [
                "020",
                "023"
            ]
        }
    ],
    "Characters": [
        {
            "label": "child (female)",
            "imagenum": [
                "003",
                "009",
                "018"
            ]
        },
        {
            "label": "thirties (male)",
            "imagenum": [
                "008",
                "015",
                "018",
                "025"
            ]
        },
        {
            "label": "twenties (female)",
            "imagenum": [
                "012",
                "020",
                "023"
            ]
        }
    ],
    "Ethnicity": [],
    "Speed": [],
    "Technique": [
        {
            "label": "animation",
            "imagenum": [
                "001",
                "002",
                "003",
                "006",
                "009",
                "012",
                "018",
                "020",
                "021"
            ]
        },
        {
            "label": "live-action",
            "imagenum": [
                "001",
                "002",
                "003",
                "006",
                "007",
                "008",
                "009",
                "011",
                "013",
                "015",
                "018",
                "019",
                "022",
                "023",
                "024",
                "025"
            ]
        }
    ],
    "Color": [
        {
            "label": "color",
            "imagenum": [
                "001",
                "002",
                "003",
                "004",
                "005",
                "006",
                "007",
                "008",
                "009",
                "011",
                "012",
                "013",
                "014",
                "015",
                "016",
                "018",
                "019",
                "020",
                "021",
                "022",
                "023",
                "024",
                "025"
            ]
        }
    ],
    "Era": [
        {
            "label": "present",
            "imagenum": [
                "001",
                "002",
                "003",
                "006",
                "007",
                "008",
                "009",
                "011",
                "012",
                "013",
                "014",
                "015",
                "016",
                "018",
                "019",
                "020",
                "021",
                "022",
                "023",
                "024",
                "025"
            ]
        }
    ],
    "Background": [
        {
            "label": "mountain",
            "imagenum": [
                "001",
                "002",
                "003",
                "004",
                "005",
                "006",
                "007",
                "008",
                "009",
                "011",
                "012",
                "013",
                "014",
                "015",
                "016",
                "018",
                "019",
                "020",
                "021",
                "022",
                "023",
                "024",
                "025"
            ]
        },
        {
            "label": "simple_background",
            "imagenum": [
                "026"
            ]
        },
        {
            "label": "nature",
            "imagenum": [
                "001",
                "002",
                "003",
                "004",
                "005",
                "006",
                "007",
                "008",
                "009",
                "011",
                "012",
                "013",
                "014",
                "015",
                "016",
                "018",
                "019",
                "020",
                "021",
                "022",
                "023",
                "024",
                "025"
            ]
        }
    ],
    "Time": [
        {
            "label": "day",
            "imagenum": [
                "001",
                "002",
                "003",
                "004",
                "005",
                "006",
                "007",
                "008",
                "009",
                "011",
                "012",
                "013",
                "014",
                "015",
                "016",
                "018",
                "019",
                "020",
                "021",
                "022",
                "023",
                "024",
                "025"
            ]
        }
    ],
    "Weather": [
        {
            "label": "clear",
            "imagenum": [
                "001",
                "002",
                "003",
                "004",
                "005",
                "006",
                "007",
                "008",
                "009",
                "011",
                "012",
                "013",
                "014",
                "015",
                "016",
                "018",
                "019",
                "020",
                "021",
                "022",
                "023",
                "024",
                "025"
            ]
        }
    ],
    "Perspective": [
        {
            "label": "third person perspective",
            "imagenum": [
                "001",
                "002",
                "003",
                "004",
                "005",
                "006",
                "007",
                "008",
                "009",
                "011",
                "012",
                "013",
                "014",
                "015",
                "016",
                "018",
                "019",
                "020",
                "021",
                "022",
                "023",
                "024",
                "025"
            ]
        }
    ]
}